Metadata-Version: 2.1
Name: pggui
Version: 0.0.1
Summary: A lib to make GUI made with PyGame
Home-page: UNKNOWN
Author: LavaPower
Author-email: lavapower84@gmail.com
License: UNKNOWN
Platform: UNKNOWN
Classifier: Programming Language :: Python
Classifier: Development Status :: 1 - Planning
